MANIFEST.in
README.rst
setup.py
src/AUTHORS.txt
src/HISTORY.txt
src/README.txt
src/sphinxjp/__init__.py
src/sphinxjp.themes.tinkerturquoisesinglecolumn.egg-info/PKG-INFO
src/sphinxjp.themes.tinkerturquoisesinglecolumn.egg-info/SOURCES.txt
src/sphinxjp.themes.tinkerturquoisesinglecolumn.egg-info/dependency_links.txt
src/sphinxjp.themes.tinkerturquoisesinglecolumn.egg-info/entry_points.txt
src/sphinxjp.themes.tinkerturquoisesinglecolumn.egg-info/namespace_packages.txt
src/sphinxjp.themes.tinkerturquoisesinglecolumn.egg-info/not-zip-safe
src/sphinxjp.themes.tinkerturquoisesinglecolumn.egg-info/requires.txt
src/sphinxjp.themes.tinkerturquoisesinglecolumn.egg-info/top_level.txt
src/sphinxjp/themes/__init__.py
src/sphinxjp/themes/tinkerturquoisesinglecolumn/__init__.py
src/sphinxjp/themes/tinkerturquoisesinglecolumn/templates/tinkerturquoisesinglecolumn/layout.html
src/sphinxjp/themes/tinkerturquoisesinglecolumn/templates/tinkerturquoisesinglecolumn/theme.conf
src/sphinxjp/themes/tinkerturquoisesinglecolumn/templates/tinkerturquoisesinglecolumn/static/pygments.css
src/sphinxjp/themes/tinkerturquoisesinglecolumn/templates/tinkerturquoisesinglecolumn/static/tinkerturquoisesinglecolumn.css_t